[
    {
        "description": "",
        "price": 0.0,
        "sales_volume": 0,
        "sales_volume_unit": "monthly"
    },
    {
        "description": "",
        "price": 0.0,
        "sales_volume": 0,
        "sales_volume_unit": "monthly"
    },
    {
        "description": "",
        "price": 0.0,
        "sales_volume": 0,
        "sales_volume_unit": "monthly"
    },
    {
        "description": "",
        "price": 0.0,
        "sales_volume": 0,
        "sales_volume_unit": "monthly"
    }
]